datachampsai/__init__.py
datachampsai/codex.py
datachampsai/datachampsai.py
datachampsai/sqlcoder.py
datachampsai-0.1.10.dist-info/licenses/LICENSE
datachampsai-0.1.10.dist-info/METADATA
datachampsai-0.1.10.dist-info/WHEEL
datachampsai-0.1.10.dist-info/entry_points.txt
datachampsai-0.1.10.dist-info/top_level.txt
datachampsai-0.1.10.dist-info/RECORD
