Metadata-Version: 2.4
Name: datachampsai
Version: 0.1.10
Summary: A Streamlit app that refines data queries using chat context and reference instructions.
Author: DataChamps
Classifier: Programming Language :: Python :: 3
Classifier: Operating System :: OS Independent
Requires-Python: >=3.7
License-File: LICENSE
Requires-Dist: streamlit
Requires-Dist: langchain
Requires-Dist: openai
Requires-Dist: langchain-openai
Dynamic: author
Dynamic: classifier
Dynamic: description
Dynamic: description-content-type
Dynamic: license-file
Dynamic: requires-dist
Dynamic: requires-python
Dynamic: summary
